spicycrab/__init__.py
spicycrab/analyzer/__init__.py
spicycrab/analyzer/type_resolver.py
spicycrab/cli.py
spicycrab/codegen/__init__.py
spicycrab/codegen/cargo.py
spicycrab/codegen/emitter.py
spicycrab/codegen/stdlib/__init__.py
spicycrab/codegen/stdlib/collections_map.py
spicycrab/codegen/stdlib/glob_map.py
spicycrab/codegen/stdlib/json_map.py
spicycrab/codegen/stdlib/os_map.py
spicycrab/codegen/stdlib/random_map.py
spicycrab/codegen/stdlib/shutil_map.py
spicycrab/codegen/stdlib/subprocess_map.py
spicycrab/codegen/stdlib/tempfile_map.py
spicycrab/codegen/stdlib/time_map.py
spicycrab/codegen/stub_discovery.py
spicycrab/cookcrab/__init__.py
spicycrab/cookcrab/_parser.cpython-311-darwin.so
spicycrab/cookcrab/cli.py
spicycrab/cookcrab/generator.py
spicycrab/cookcrab/py.typed
spicycrab/ir/__init__.py
spicycrab/ir/nodes.py
spicycrab/macros/__init__.py
spicycrab/macros/attributes.py
spicycrab/macros/decorator.py
spicycrab/macros/traits.py
spicycrab/parser/__init__.py
spicycrab/parser/python_ast.py
spicycrab/parser/type_parser.py
spicycrab/types/__init__.py
spicycrab/types/error.py
spicycrab/types/option.py
spicycrab/types/result.py
spicycrab/utils/__init__.py
spicycrab/utils/errors.py
spicycrab-0.0.1.dist-info/METADATA
spicycrab-0.0.1.dist-info/WHEEL
spicycrab-0.0.1.dist-info/entry_points.txt
spicycrab-0.0.1.dist-info/RECORD
