Metadata-Version: 2.4
Name: spicycrab
Version: 0.0.1
Classifier: Development Status :: 3 - Alpha
Classifier: Intended Audience :: Developers
Classifier: License :: OSI Approved :: MIT License
Classifier: Programming Language :: Python :: 3
Classifier: Programming Language :: Python :: 3.10
Classifier: Programming Language :: Python :: 3.11
Classifier: Programming Language :: Python :: 3.12
Classifier: Topic :: Software Development :: Compilers
Requires-Dist: build>=1.0.0
Requires-Dist: click>=8.0
Requires-Dist: jinja2>=3.0
Requires-Dist: pytest>=7.0 ; extra == 'dev'
Requires-Dist: pytest-cov>=4.0 ; extra == 'dev'
Requires-Dist: mypy>=1.0 ; extra == 'dev'
Requires-Dist: ruff>=0.1.0 ; extra == 'dev'
Requires-Dist: sphinx>=7.0 ; extra == 'docs'
Requires-Dist: sphinx-rtd-theme>=2.0 ; extra == 'docs'
Requires-Dist: sphinx-copybutton>=0.5 ; extra == 'docs'
Requires-Dist: myst-parser>=2.0 ; extra == 'docs'
Provides-Extra: dev
Provides-Extra: docs
Summary: A Python to Rust transpiler for type-annotated Python code
Keywords: python,rust,transpiler,compiler
Author: spicycrab contributors
License: MIT
Requires-Python: >=3.10
Project-URL: Homepage, https://github.com/kushaldas/spicycrab
